Metadata-Version: 1.1
Name: petitzway
Version: 0.0.5
Summary: Python module for Z-Way API
Home-page: https://github.com/PetitCircuitLab/petitzway
Author: Fredrik Haglund
Author-email: fredrik@petitcircuitlab.com
License: BSD
Keywords: zwave,zway,z-way
Platform: UNKNOWN
Classifier: License :: OSI Approved :: BSD License
Classifier: Programming Language :: Python :: 3 :: Only
